barentsz/__init__.py
barentsz/_attribute.py
barentsz/_discover.py
barentsz/_here.py
barentsz/_meta.py
barentsz/_typings.py
barentsz-1.2.1.dist-info/LICENSE
barentsz-1.2.1.dist-info/METADATA
barentsz-1.2.1.dist-info/WHEEL
barentsz-1.2.1.dist-info/top_level.txt
barentsz-1.2.1.dist-info/RECORD
