Metadata-Version: 2.1
Name: barentsz
Version: 1.2.1
Summary: For discovering modules, classes, functions and attributes.
Home-page: https://github.com/ramonhagenaars/barentsz
Author: Ramon Hagenaars
Author-email: ramon.hagenaars@gmail.com
License: MIT
Platform: UNKNOWN
Classifier: Intended Audience :: Developers
Classifier: License :: OSI Approved :: MIT License
Classifier: Operating System :: OS Independent
Classifier: Natural Language :: English
Classifier: Programming Language :: Python
Classifier: Programming Language :: Python :: 3
Classifier: Programming Language :: Python :: 3.6
Classifier: Programming Language :: Python :: 3.7
Classifier: Programming Language :: Python :: 3.8
Requires-Python: >=3.6
Requires-Dist: typish (>=1.7.0)
Provides-Extra: test
Requires-Dist: scons ; extra == 'test'
Requires-Dist: pycodestyle ; extra == 'test'
Requires-Dist: pylint ; extra == 'test'
Requires-Dist: mypy ; extra == 'test'
Requires-Dist: pytest ; extra == 'test'
Requires-Dist: pytest-cov ; extra == 'test'
Requires-Dist: coverage ; extra == 'test'
Requires-Dist: radon ; extra == 'test'
Requires-Dist: xenon ; extra == 'test'
Requires-Dist: autoflake ; extra == 'test'
Requires-Dist: isort ; extra == 'test'
